{
    "SuperAdmin": {
        "dashboard": true,
        "pois_view": true,
        "pois_create": true,
        "pois_edit": true,
        "pois_delete": true,
        "restaurants_view": true,
        "restaurants_manage": true,
        "narrations_view": true,
        "narrations_manage": true,
        "users_view": true,
        "users_manage": true,
        "analytics_view": true,
        "media_manage": true,
        "settings_view": true,
        "settings_edit": true,
        "logs_view": true,
        "notifications_send": true,
        "backup_manage": true
    },
    "Admin": {
        "dashboard": true,
        "pois_view": true,
        "pois_create": true,
        "pois_edit": true,
        "pois_delete": true,
        "restaurants_view": true,
        "restaurants_manage": true,
        "narrations_view": true,
        "narrations_manage": true,
        "users_view": true,
        "users_manage": true,
        "analytics_view": true,
        "media_manage": true,
        "settings_view": true,
        "settings_edit": true,
        "logs_view": true,
        "notifications_send": true,
        "backup_manage": true
    },
    "Editor": {
        "dashboard": true,
        "pois_view": true,
        "pois_create": true,
        "pois_edit": true,
        "pois_delete": false,
        "restaurants_view": true,
        "restaurants_manage": true,
        "narrations_view": true,
        "narrations_manage": true,
        "users_view": false,
        "users_manage": false,
        "analytics_view": true,
        "media_manage": true,
        "settings_view": false,
        "settings_edit": false,
        "logs_view": false,
        "notifications_send": false,
        "backup_manage": false
    },
    "Moderator": {
        "dashboard": true,
        "pois_view": true,
        "pois_create": false,
        "pois_edit": false,
        "pois_delete": false,
        "restaurants_view": true,
        "restaurants_manage": false,
        "narrations_view": true,
        "narrations_manage": false,
        "users_view": true,
        "users_manage": false,
        "analytics_view": true,
        "media_manage": false,
        "settings_view": false,
        "settings_edit": false,
        "logs_view": true,
        "notifications_send": false,
        "backup_manage": false
    },
    "Viewer": {
        "dashboard": true,
        "pois_view": true,
        "pois_create": false,
        "pois_edit": false,
        "pois_delete": false,
        "restaurants_view": true,
        "restaurants_manage": false,
        "narrations_view": true,
        "narrations_manage": false,
        "users_view": false,
        "users_manage": false,
        "analytics_view": true,
        "media_manage": false,
        "settings_view": false,
        "settings_edit": false,
        "logs_view": false,
        "notifications_send": false,
        "backup_manage": false
    }
}